siriusbackbone/__init__.py
siriusbackbone/backbone.py
siriusbackbone-1.0.3.dist-info/METADATA
siriusbackbone-1.0.3.dist-info/WHEEL
siriusbackbone-1.0.3.dist-info/top_level.txt
siriusbackbone-1.0.3.dist-info/RECORD
