Metadata-Version: 2.1
Name: siriusbackbone
Version: 1.0.3
Summary: Backbone in Pytorch
Home-page: https://github.com/siriusdemon/private/hackaway
Author: sirius demon
Author-email: mory2016@126.com
License: UNKNOWN
Platform: UNKNOWN
Classifier: Programming Language :: Python :: 3
Classifier: License :: OSI Approved :: BSD License
Classifier: Operating System :: OS Independent
